shapesorter/__init__.py
shapesorter/shapesorter.py
shapesorter-0.1.0.dist-info/LICENSE
shapesorter-0.1.0.dist-info/METADATA
shapesorter-0.1.0.dist-info/WHEEL
shapesorter-0.1.0.dist-info/entry_points.txt
shapesorter-0.1.0.dist-info/top_level.txt
shapesorter-0.1.0.dist-info/RECORD
